Metadata-Version: 2.4
Name: alphafold3-pytorch
Version: 0.7.12
Summary: Alphafold 3 - Pytorch
Project-URL: Homepage, https://pypi.org/project/alphafold3-pytorch/
Project-URL: Repository, https://github.com/lucidrains/alphafold3-pytorch
Author-email: Phil Wang <lucidrains@gmail.com>, Alex Morehead <alex.morehead@gmail.com>
License: MIT License
License-File: LICENSE
Keywords: artificial intelligence,deep learning,protein structure prediction
Classifier: Development Status :: 4 - Beta
Classifier: Intended Audience :: Developers
Classifier: License :: OSI Approved :: MIT License
Classifier: Programming Language :: Python :: 3.9
Classifier: Topic :: Scientific/Engineering :: Artificial Intelligence
Requires-Python: >=3.9
Requires-Dist: adam-atan2-pytorch>=0.1.12
Requires-Dist: awscliv2>=2.3.1
Requires-Dist: beartype
Requires-Dist: biopython>=1.83
Requires-Dist: cachetools
Requires-Dist: click>=8.1
Requires-Dist: colt5-attention>=0.11.0
Requires-Dist: einops>=0.8.0
Requires-Dist: einx>=0.2.2
Requires-Dist: ema-pytorch>=0.7.0
Requires-Dist: environs
Requires-Dist: fair-esm
Requires-Dist: fastapi
Requires-Dist: frame-averaging-pytorch>=0.0.18
Requires-Dist: gemmi>=0.6.6
Requires-Dist: gradio
Requires-Dist: gradio-molecule3d
Requires-Dist: huggingface-hub>=0.21.4
Requires-Dist: hyper-connections>=0.0.23
Requires-Dist: jaxtyping>=0.2.28
Requires-Dist: joblib
Requires-Dist: lightning>=2.2.5
Requires-Dist: lion-pytorch>=0.2.2
Requires-Dist: loguru
Requires-Dist: multimolecule==0.0.5
Requires-Dist: nimporter
Requires-Dist: numpy>=1.23.5
Requires-Dist: pdbeccdutils>=0.8.5
Requires-Dist: polars>=1.1.0
Requires-Dist: pydantic>=2.8.2
Requires-Dist: pyyaml
Requires-Dist: rdkit>=2023.9.6
Requires-Dist: retrying
Requires-Dist: scikit-learn>=1.5.0
Requires-Dist: scipy==1.13.1
Requires-Dist: sentencepiece
Requires-Dist: sh>=2.0.7
Requires-Dist: shortuuid
Requires-Dist: taylor-series-linear-attention>=0.1.12
Requires-Dist: tensorboard
Requires-Dist: timeout-decorator>=0.5.0
Requires-Dist: torch-geometric
Requires-Dist: torch>=2.1
Requires-Dist: torchtyping>=0.1.5
Requires-Dist: tqdm>=4.66.4
Requires-Dist: transformers[torch]
Provides-Extra: examples
Provides-Extra: test
Requires-Dist: pytest; extra == 'test'
Requires-Dist: pytest-shard; extra == 'test'
Requires-Dist: ruff>=0.4.2; extra == 'test'
